mlflow/__init__.py
mlflow/__main__.py
mlflow/cli.py
mlflow/client.py
mlflow/db.py
mlflow/environment_variables.py
mlflow/exceptions.py
mlflow/experiments.py
mlflow/ml_package_versions.py
mlflow/py.typed
mlflow/pypi_package_index.json
mlflow/runs.py
mlflow/version.py
mlflow/artifacts/__init__.py
mlflow/autogen/__init__.py
mlflow/autogen/autogen_logger.py
mlflow/azure/__init__.py
mlflow/azure/client.py
mlflow/catboost/__init__.py
mlflow/config/__init__.py
mlflow/data/__init__.py
mlflow/data/artifact_dataset_sources.py
mlflow/data/code_dataset_source.py
mlflow/data/dataset.py
mlflow/data/dataset_registry.py
mlflow/data/dataset_source.py
mlflow/data/dataset_source_registry.py
mlflow/data/delta_dataset_source.py
mlflow/data/digest_utils.py
mlflow/data/evaluation_dataset.py
mlflow/data/filesystem_dataset_source.py
mlflow/data/http_dataset_source.py
mlflow/data/huggingface_dataset.py
mlflow/data/huggingface_dataset_source.py
mlflow/data/meta_dataset.py
mlflow/data/numpy_dataset.py
mlflow/data/pandas_dataset.py
mlflow/data/pyfunc_dataset_mixin.py
mlflow/data/schema.py
mlflow/data/sources.py
mlflow/data/spark_dataset.py
mlflow/data/spark_dataset_source.py
mlflow/data/spark_delta_utils.py
mlflow/data/tensorflow_dataset.py
mlflow/data/uc_volume_dataset_source.py
mlflow/deployments/__init__.py
mlflow/deployments/base.py
mlflow/deployments/cli.py
mlflow/deployments/constants.py
mlflow/deployments/interface.py
mlflow/deployments/plugin_manager.py
mlflow/deployments/utils.py
mlflow/deployments/databricks/__init__.py
mlflow/deployments/mlflow/__init__.py
mlflow/deployments/openai/__init__.py
mlflow/deployments/server/__init__.py
mlflow/deployments/server/app.py
mlflow/deployments/server/config.py
mlflow/deployments/server/constants.py
mlflow/deployments/server/runner.py
mlflow/diviner/__init__.py
mlflow/entities/__init__.py
mlflow/entities/_mlflow_object.py
mlflow/entities/assessment.py
mlflow/entities/assessment_source.py
mlflow/entities/dataset.py
mlflow_no_ssl-2.16.3.dist-info/LICENSE.txt
mlflow_no_ssl-2.16.3.dist-info/METADATA
mlflow_no_ssl-2.16.3.dist-info/WHEEL
mlflow_no_ssl-2.16.3.dist-info/entry_points.txt
mlflow_no_ssl-2.16.3.dist-info/top_level.txt
mlflow_no_ssl-2.16.3.dist-info/RECORD
