Metadata-Version: 2.1
Name: mlflow-no-ssl
Version: 2.16.3
Summary: MLflow is an open source platform for the complete machine learning lifecycle
Maintainer-email: Databricks <mlflow-oss-maintainers@googlegroups.com>
License: Copyright 2018 Databricks, Inc.  All rights reserved.
Project-URL: homepage, https://mlflow.org
Project-URL: issues, https://github.com/mlflow/mlflow/issues
Project-URL: documentation, https://mlflow.org/docs/latest/index.html
Project-URL: repository, https://github.com/mlflow/mlflow
Keywords: mlflow,ai,databricks
Classifier: Development Status :: 5 - Production/Stable
Classifier: Intended Audience :: Developers
Classifier: Intended Audience :: End Users/Desktop
Classifier: Intended Audience :: Science/Research
Classifier: Intended Audience :: Information Technology
Classifier: Topic :: Scientific/Engineering :: Artificial Intelligence
Classifier: Topic :: Software Development :: Libraries :: Python Modules
Classifier: License :: OSI Approved :: Apache Software License
Classifier: Operating System :: OS Independent
Classifier: Programming Language :: Python :: 3.8
Requires-Python: >=3.8
License-File: LICENSE.txt
Requires-Dist: Flask<4
Requires-Dist: alembic!=1.10.0,<2
Requires-Dist: cachetools<6,>=5.0.0
Requires-Dist: click<9,>=7.0
Requires-Dist: cloudpickle<4
Requires-Dist: databricks-sdk<1,>=0.20.0
Requires-Dist: docker<8,>=4.0.0
Requires-Dist: gitpython<4,>=3.1.9
Requires-Dist: graphene<4
Requires-Dist: importlib-metadata!=4.7.0,<9,>=3.7.0
Requires-Dist: markdown<4,>=3.3
Requires-Dist: matplotlib<4
Requires-Dist: numpy<3
Requires-Dist: opentelemetry-api<3,>=1.9.0
Requires-Dist: opentelemetry-sdk<3,>=1.9.0
Requires-Dist: packaging<25
Requires-Dist: pandas<3
Requires-Dist: protobuf<6,>=3.12.0
Requires-Dist: pyarrow<18,>=4.0.0
Requires-Dist: pyyaml<7,>=5.1
Requires-Dist: requests<3,>=2.17.3
Requires-Dist: scikit-learn<2
Requires-Dist: scipy<2
Requires-Dist: sqlalchemy<3,>=1.4.0
Requires-Dist: sqlparse<1,>=0.4.0
Requires-Dist: Jinja2<4,>=2.11; platform_system != "Windows"
Requires-Dist: gunicorn<24; platform_system != "Windows"
Requires-Dist: Jinja2<4,>=3.0; platform_system == "Windows"
Requires-Dist: waitress<4; platform_system == "Windows"
Provides-Extra: aliyun-oss
Requires-Dist: aliyunstoreplugin; extra == "aliyun-oss"
Provides-Extra: databricks
Requires-Dist: azure-storage-file-datalake>12; extra == "databricks"
Requires-Dist: google-cloud-storage>=1.30.0; extra == "databricks"
Requires-Dist: boto3>1; extra == "databricks"
Requires-Dist: botocore; extra == "databricks"
Provides-Extra: extras
Requires-Dist: pyarrow; extra == "extras"
Requires-Dist: requests-auth-aws-sigv4; extra == "extras"
Requires-Dist: boto3; extra == "extras"
Requires-Dist: botocore; extra == "extras"
Requires-Dist: google-cloud-storage>=1.30.0; extra == "extras"
Requires-Dist: azureml-core>=1.2.0; extra == "extras"
Requires-Dist: pysftp; extra == "extras"
Requires-Dist: kubernetes; extra == "extras"
Requires-Dist: virtualenv; extra == "extras"
Requires-Dist: prometheus-flask-exporter; extra == "extras"
Provides-Extra: gateway
Requires-Dist: pydantic<3,>=1.0; extra == "gateway"
Requires-Dist: fastapi<1; extra == "gateway"
Requires-Dist: uvicorn[standard]<1; extra == "gateway"
Requires-Dist: watchfiles<1; extra == "gateway"
Requires-Dist: aiohttp<4; extra == "gateway"
Requires-Dist: boto3<2,>=1.28.56; extra == "gateway"
Requires-Dist: tiktoken<1; extra == "gateway"
Requires-Dist: slowapi<1,>=0.1.9; extra == "gateway"
Provides-Extra: genai
Requires-Dist: pydantic<3,>=1.0; extra == "genai"
Requires-Dist: fastapi<1; extra == "genai"
Requires-Dist: uvicorn[standard]<1; extra == "genai"
Requires-Dist: watchfiles<1; extra == "genai"
Requires-Dist: aiohttp<4; extra == "genai"
Requires-Dist: boto3<2,>=1.28.56; extra == "genai"
Requires-Dist: tiktoken<1; extra == "genai"
Requires-Dist: slowapi<1,>=0.1.9; extra == "genai"
Provides-Extra: jfrog
Requires-Dist: mlflow-jfrog-plugin; extra == "jfrog"
Provides-Extra: langchain
Requires-Dist: langchain<=0.2.15,>=0.1.0; extra == "langchain"
Provides-Extra: mlserver
Requires-Dist: mlserver!=1.3.1,>=1.2.0; extra == "mlserver"
Requires-Dist: mlserver-mlflow!=1.3.1,>=1.2.0; extra == "mlserver"
Provides-Extra: sqlserver
Requires-Dist: mlflow-dbstore; extra == "sqlserver"
Provides-Extra: xethub
Requires-Dist: mlflow-xethub; extra == "xethub"
